glci_stats/__init__.py
glci_stats/__main__.py
glci_stats/cli.py
glci_stats-1.1.1.dist-info/METADATA
glci_stats-1.1.1.dist-info/WHEEL
glci_stats-1.1.1.dist-info/entry_points.txt
glci_stats-1.1.1.dist-info/top_level.txt
glci_stats-1.1.1.dist-info/RECORD
