Metadata-Version: 2.1
Name: glci-stats
Version: 1.1.1
Summary: Utility to collect stats about your Gitlab CI performance
Author-email: Alexander Bespalov <discrimy.off@gmail.com>
License: MIT
Project-URL: Homepage, https://github.com/discrimy/glci-stats
Project-URL: Issues, https://github.com/discrimy/glci-stats/issues
Keywords: gitlab,ci,jobs,statistics,cli
Classifier: Intended Audience :: Developers
Classifier: License :: OSI Approved :: MIT License
Classifier: Environment :: Console
Classifier: Programming Language :: Python :: 3
Classifier: Programming Language :: Python :: 3 :: Only
Classifier: Programming Language :: Python :: 3.8
Classifier: Programming Language :: Python :: 3.9
Classifier: Programming Language :: Python :: 3.10
Classifier: Programming Language :: Python :: 3.11
Classifier: Programming Language :: Python :: 3.12
Requires-Python: >=3.8
